humantic/__init__.py
humantic/cli.py
humantic/client.py
humanticclient-0.1.3.dist-info/METADATA
humanticclient-0.1.3.dist-info/WHEEL
humanticclient-0.1.3.dist-info/entry_points.txt
humanticclient-0.1.3.dist-info/licenses/LICENSE
humanticclient-0.1.3.dist-info/RECORD
