Metadata-Version: 2.4
Name: humanticclient
Version: 0.1.3
Summary: Python client for Humantic AI API - Analyze LinkedIn profiles for sales and hiring insights
Project-URL: Homepage, https://github.com/ifightcode/Humantic-Client
Project-URL: Repository, https://github.com/ifightcode/Humantic-Client
Project-URL: Issues, https://github.com/ifightcode/Humantic-Client/issues
Author: Tanmoy Sadhukhan
License: MIT
License-File: LICENSE
Keywords: ai,analysis,hiring,humantic,linkedin,profile,sales
Classifier: Development Status :: 4 - Beta
Classifier: Intended Audience :: Developers
Classifier: License :: OSI Approved :: MIT License
Classifier: Programming Language :: Python :: 3
Classifier: Programming Language :: Python :: 3.12
Classifier: Programming Language :: Python :: 3.13
Classifier: Topic :: Software Development :: Libraries :: Python Modules
Requires-Python: >=3.12
Requires-Dist: httpx>=0.27.0
Requires-Dist: python-dotenv>=1.0.0
Provides-Extra: cli
Requires-Dist: click>=8.0.0; extra == 'cli'
